[
  { "time": 24.3, "text": "سلام خانم دکتر یه دوگانگیم من" },
  { "time": 27.3, "text": "تو ذهنم راجع به رفتارام سواله بیش از حد" },
  { "time": 30.1, "text": "چرا یهو ترس میگیرتم سراغ چی هستم" },
  { "time": 33.3, "text": "بعد عشق به زندگی میگیرم دوباره میخندم" },
  { "time": 36.3, "text": "تو تنهاییام دلم میخواد آدم باشه دورم" },
  {
    "time": 39.1,
    "text": "ولی پر که میشه دورم میخوام باشم مال خودم"
  },
  { "time": 42.3, "text": "بچپم تو دفتر" },
  { "time": 43.8, "text": "بالا پایین اینستا" },
  { "time": 45.6, "text": "نکنم هیچ کار" },
  { "time": 46.8, "text": "پا لپ تاپ و یه فیلم باز" },
  { "time": 48.3, "text": "ولی فیلمم پخش بشه فکرم صد جای دیگه س" },
  {
    "time": 51,
    "text": "نمیتونم توصیف کنم فکرام درباره چی هست"
  },
  { "time": 54.3, "text": "یه سری بیهودگین و افکار بی ربط" },
  { "time": 57.3, "text": "تو موقعیتای دیگه همواره گیرم" },
  { "time": 60.3, "text": "یه دوگانگیم میخورم حسرت" },
  { "time": 62.5, "text": "بعد تو موقعیت که باشم میکنم دست دست" },
  { "time": 65.5, "text": "من یه روحیه ای دارم که همیشه خسته س" },
  { "time": 68.5, "text": "نه حوصله پیشرفت داره و نه میخواد پسرفت هم" },
  { "time": 72.2, "text": "حواسم نیست هی میگذره" },
  { "time": 75.2, "text": "حواسم هست هی میگذره" },
  { "time": 78, "text": "یه رو رو مودم هی میگذره" },
  { "time": 81, "text": "یه رو بی مودم باز میگذره" },
  { "time": 84.1, "text": "میشم خوشحال زود میگذره" },
  { "time": 87, "text": "میبافم رویا باد میبره" },
  { "time": 89.8, "text": "اصن حواسم نیست هی میگذره" },
  { "time": 92.3, "text": "هی میگذره" },
  { "time": 93.8, "text": "هی میگذره" },
  { "time": 96.1, "text": "با یه ته دل خالی و یه تنهایی تو جمع" },
  { "time": 99.3, "text": "با دوستا یا خانواده م و صد جا دیگه روحم" },
  { "time": 102.3, "text": "خوشیامو میذارم گرو هر کاری که توشم" },
  { "time": 105.3, "text": "میگم بمونه برا بعد فردایی که خوبم" },
  { "time": 108.3, "text": "خلاصه خانم دکتر من یه چند گانگیم" },
  { "time": 111.1, "text": "با شما که حرف میزنم الان صد جای دیگه م" },
  { "time": 114.1, "text": "و پر اتفاقه سرم" },
  { "time": 115.8, "text": "اضطرابه همه ش؟" },
  { "time": 117.3, "text": "مث من بیمار داشتی؟" },
  { "time": 118.6, "text": "اینا اشتباهه اصن؟" },
  { "time": 120.1, "text": "یکی خوب که میگه ازم فکر میکنم نیست حقم" },
  { "time": 123.3, "text": "از حرف زدن جلو جمع آدما میترسم" },
  { "time": 126.2, "text": "چون میلرزه صدام میشه ته دلم خالی" },
  { "time": 129.3, "text": "گر میگیره پوستم انگار دارم میجنگم" },
  { "time": 132.3, "text": "کی گفته که زندگی باید باشه انقد سخت" },
  { "time": 135.3, "text": "کی گفته که من مجبور باشم دائم بجنگم" },
  { "time": 138.3, "text": "که گفته که باس کنم کل وقت و صرف هدف" },
  { "time": 141.3, "text": "که گناه میره تو وجودم کنم وقت و تلف" },
  { "time": 144.3, "text": "عقربه هی میپره" },
  { "time": 147.2, "text": "حواسم نیست میگذره" },
  { "time": 150.3, "text": "رویاهام و باد میبره" },
  { "time": 153.1, "text": "حواسم نیست میگذره" },
  { "time": 156.3, "text": "حواسم هست میگذره" },
  { "time": 159.2, "text": "حواسم نیست میگذره" },
  { "time": 161.8, "text": "اصن حواسم نیست میگذره" },
  { "time": 164.6, "text": "هی میگذره" },
  { "time": 165.8, "text": "هی میگذره" },
  { "time": 167.5, "text": "یه غریبه صد بارم بهم بد کنه به جوش نمیام من" },
  { "time": 171.3, "text": "یکی حقمو بخوره به روش نمیارم" },
  { "time": 174.1, "text": "یه تنش ریزی که بشه یه روز نمیخوابم" },
  { "time": 177.3, "text": "میترسم" },
  { "time": 178, "text": "میترسم" },
  { "time": 178.7, "text": "میترسم" },
  { "time": 179.4, "text": "میترسم" },
  { "time": 180, "text": "همزمان چند نفر حرف بزنن فلج میشه مغزم" },
  { "time": 183.3, "text": "جواب همه هم و ببینیما نه عه حتما" },
  { "time": 186, "text": "ولی نمیتونم نه رو بگم میپیچونم فقط" },
  { "time": 189.3, "text": "میترسم" },
  { "time": 190, "text": "میترسم" },
  { "time": 190.7, "text": "میترسم" },
  { "time": 191.4, "text": "میترسم" },
  { "time": 192.3, "text": "درک از جهان برامه کم و بیش مبهم" },
  { "time": 195.3, "text": "چیزای مهمی و گاها سبک میشمرم" },
  {
    "time": 198.1,
    "text": "ولی یه سری چیزای ریزی میشه برام گنده"
  },
  { "time": 201.3, "text": "متوجهم بعضی وقتا چقد کارام کنده" },
  { "time": 204.3, "text": "یه چیزی که نباید گاهی میشه یه ساعت" },
  { "time": 207.3, "text": "یه کار معمولی و کشش میدم چهار ماه" },
  { "time": 210.3, "text": "یه تمیز کردن خونه واسمه سه ساعت" },
  { "time": 213.2, "text": "یه هدف و پی خودم میکشمش تا سال ها" },
  { "time": 217, "text": "" },
  { "time": 228.3, "text": "این استرس و اضطرابا داعمیه همرام" },
  { "time": 231.3, "text": "که لابلا این فکرای هر روزه گمه معنا" },
  { "time": 234.3, "text": "بزرگ شدیم و کردیم به روزمرگی عادت" },
  { "time": 237.3, "text": "نفهمیدیم چی شد زندگی نمیدونم شاید" },
  { "time": 240.1, "text": "زندگی همین خوشیه تو لحظه های ریز" },
  { "time": 243.1, "text": "همین حرف زدن با آدماس تو پرسه ها یه ریز" },
  { "time": 246.3, "text": "خاطرات کودکی و تک ستاره بیست" },
  { "time": 249.1, "text": "همون رویاعه که میبافیم یه طرح ناب بریز" },
  { "time": 252.2, "text": "شاید همینه که پاشیم حتی بعد سخت تریناش" },
  { "time": 255.4, "text": "لذت انجام کاری واسه اولین بار" },
  { "time": 258.3, "text": "گاهی شاید غمه حتی خود غمم زیباس" },
  { "time": 261, "text": "اصن ارزش لحظه های خوب ما از همیناس" },
  { "time": 264.3, "text": "غم هم میگذره" },
  { "time": 267.3, "text": "همه چی میگذره" },
  { "time": 270.3, "text": "" },
  { "time": 271, "text": "" }
]
